.dockerignore
.gitignore
CHANGELOG.md
LICENSE
MANIFEST.in
README.md
requirements.txt
setup.py
.github/workflows/main.yml
markovmeme/__init__.py
markovmeme/_main.py
markovmeme/client.py
markovmeme/gil.py
markovmeme/main.py
markovmeme/namer.py
markovmeme/text.py
markovmeme/utils.py
markovmeme/version.py
markovmeme.egg-info/PKG-INFO
markovmeme.egg-info/SOURCES.txt
markovmeme.egg-info/dependency_links.txt
markovmeme.egg-info/entry_points.txt
markovmeme.egg-info/not-zip-safe
markovmeme.egg-info/requires.txt
markovmeme.egg-info/top_level.txt
markovmeme/data/corpus/dr_seuss.txt
markovmeme/data/corpus/hamlet.txt
markovmeme/data/corpus/the_office.txt
markovmeme/data/corpus/trump_speech.txt
markovmeme/data/corpus/office/andy.txt
markovmeme/data/corpus/office/angela.txt
markovmeme/data/corpus/office/charles.txt
markovmeme/data/corpus/office/clark.txt
markovmeme/data/corpus/office/creed.txt
markovmeme/data/corpus/office/darryl.txt
markovmeme/data/corpus/office/david.txt
markovmeme/data/corpus/office/deangelo.txt
markovmeme/data/corpus/office/dwight.txt
markovmeme/data/corpus/office/erin.txt
markovmeme/data/corpus/office/gabe.txt
markovmeme/data/corpus/office/holly.txt
markovmeme/data/corpus/office/jan.txt
markovmeme/data/corpus/office/jim.txt
markovmeme/data/corpus/office/jo.txt
markovmeme/data/corpus/office/karen.txt
markovmeme/data/corpus/office/kelly.txt
markovmeme/data/corpus/office/kevin.txt
markovmeme/data/corpus/office/meredith.txt
markovmeme/data/corpus/office/michael.txt
markovmeme/data/corpus/office/nellie.txt
markovmeme/data/corpus/office/office.json
markovmeme/data/corpus/office/office_transcript.csv
markovmeme/data/corpus/office/oscar.txt
markovmeme/data/corpus/office/pam.txt
markovmeme/data/corpus/office/pete.txt
markovmeme/data/corpus/office/phyllis.txt
markovmeme/data/corpus/office/prepare.py
markovmeme/data/corpus/office/robert.txt
markovmeme/data/corpus/office/roy.txt
markovmeme/data/corpus/office/ryan.txt
markovmeme/data/corpus/office/stanley.txt
markovmeme/data/corpus/office/toby.txt
markovmeme/data/images/dr_seuss1.png
markovmeme/data/images/dr_seuss2.png
markovmeme/data/images/dr_seuss3.png
markovmeme/data/images/dr_seuss4.png
markovmeme/data/images/dr_seuss5.png
