Metadata-Version: 2.1
Name: markovmeme
Version: 0.0.1
Summary: Command line tool for generating markov memes.
Home-page: http://www.github.com/vsoch/markovmeme
Author: Vanessa Sochat
Author-email: vsochat@stanford.edu
Maintainer: Vanessa Sochat
Maintainer-email: vsochat@stanford.edu
License: LICENSE
Keywords: generate memes using a Markov Model
Platform: UNKNOWN
Classifier: Intended Audience :: Science/Research
Classifier: Intended Audience :: Developers
Classifier: License :: OSI Approved :: Mozilla Public License 2.0 (MPL 2.0)
Classifier: Programming Language :: Python
Classifier: Topic :: Software Development
Classifier: Topic :: Scientific/Engineering
Classifier: Operating System :: Unix
Classifier: Programming Language :: Python :: 3.7
